blatt_05/mit Timer/ampel.vhd
entity ampel is
	port(clk, reset, ns_detektor, wo_detektor: in bit;
		ns_ampel, wo_ampel: out bit_vector(2 downto 0));
end ampel;

architecture behave of ampel is

--ns_g -> nord-sued ist gruen
--ns_r -> nord-sued ist rot
--ns_ry -> nord-sued ist rot-gelb
--ns_y -> nord-sued ist gelb
--entsprechende Benennung fuer wo
type T_STATE is (s_off, s_ns_r_wo_r, s_ns_g_wo_r, s_ns_y_wo_ry, s_ns_r_wo_g, s_ns_ry_wo_y);
signal NEXT_STATE : T_STATE;
signal STATE: T_STATE := s_off;
signal timeout_start, timeout_ack, timeout: bit;
signal timeout_type: bit_vector (1 downto 0);
signal counter : integer := 0;

begin 

fsm:	process(STATE, clk)
	begin
	
	if clk'event and clk='1' then
		if reset = '1' then
			--reset führt in den Zustand, in dem beide Ampeln rot sind
			NEXT_STATE <= s_ns_r_wo_r;
			ns_ampel <= "001";
			wo_ampel <= "001";
		else
			case STATE is
				when s_off =>
				when s_ns_r_wo_r =>
					--ohne trigger direkt ns Ampel im nächsten State auf grün
					--starte Timer, um Ampel mind. 30 Sekunden grün zu halten
					NEXT_STATE <= s_ns_g_wo_r;
					timeout_type <= "11";
					timeout_start <= '1';
					ns_ampel <= "100";
					wo_ampel <= "001";	
				when s_ns_g_wo_r =>
					timeout_start <= '0'; --reset des startsignals
					--blockade, falls timeout noch nicht kam
					if wo_detektor = '1' and timeout='1' then
						NEXT_STATE <= s_ns_y_wo_ry;
						ns_ampel <= "010";
						wo_ampel <= "011";
					end if;
				when s_ns_y_wo_ry =>
					--starte Timer, um Ampel mind. 20 Sekunden grün zu halten
					NEXT_STATE <= s_ns_r_wo_g;
					timeout_type <= "10";
					timeout_start <= '1';
					ns_ampel <= "001";
					wo_ampel <= "100";
				when s_ns_r_wo_g =>
					timeout_start <= '0'; --reset des startsignals
					--blockade, falls timeout noch nicht kam
					if ns_detektor = '1' and timeout='1' then
						NEXT_STATE <= s_ns_ry_wo_y;
						ns_ampel <= "011";
						wo_ampel <= "010";
					end if;
				when s_ns_ry_wo_y =>
					--starte Timer, um Ampel mind. 30 Sekunden grün zu halten
					NEXT_STATE <= s_ns_g_wo_r;
					timeout_type <= "11";
					timeout_start <= '1';
					ns_ampel <= "100";
					wo_ampel <= "001";
			end case;
		end if;
	end if;		
end process fsm;

REG: 	process(clk)
	begin
	--state an fallender taktflanke aendern, damit ein Zustandswechsel keine 2 Takte braucht
	if clk'event and clk='0' then
		if timeout_start = '1' then
			--blockieren, falls timeout angefordert aber noch nicht acknowledged wurde
			if timeout_ack='1' then
				STATE <= NEXT_STATE;
			end if;
		else
			STATE <= NEXT_STATE;
		end if;
	end if;
end process REG;

timer: 	process(clk)
	begin
	if clk'event and clk='1' then
		timeout <= '0';
		if timeout_start='1' then
			--sende ack zurück
			timeout_ack <= '1';			
			if timeout_type="10" then --20 Sekunden
				counter <= 1;
			elsif timeout_type="11" then --30 Sekunden
				counter <= 3;
			end if;
		else		
			if counter = 1 then
				timeout <= '1';
				timeout_ack <= '0';
			elsif counter > 1 then
				counter <= counter - 1;
			end if;
		end if;
	end if;
end process timer;
end behave;

blatt_05/mit Timer/testbench.vhd
entity testbench is
end testbench;

architecture behave of testbench is
component ampel is
	port(clk, reset, ns_detektor, wo_detektor: in bit;
        	ns_ampel, wo_ampel: out bit_vector(2 downto 0));
end component;

signal clk, reset, ns_detektor, wo_detektor: bit := '0';
signal ns_ampel, wo_ampel: bit_vector(2 downto 0);

begin

DUS: entity work.ampel port map (clk, reset, ns_detektor, wo_detektor, ns_ampel, wo_ampel);

clk <= NOT clk after 2500 ms;

stimulate : process
	begin
	wait until clk'event and clk='1';
	reset <= '1';
	wait until clk'event and clk='1';
	reset <= '0';
	wait until clk'event and clk='1' and ns_ampel = "100";
	
	-- extremfall: so viele autos, dass die Detektoren immer Autos anzeigen
	-- die Ampel halten also exakt 30 bzw 20 Sekunden lang grün bevor sie wechseln

	wo_detektor <= '1';
	ns_detektor <= '1';	

	wait;
end process stimulate;
end behave;

blatt_05/mit Timer/testbench.vcd
$date
	Fri Jun 16 21:02:39 2017
$end
$version
	QuestaSim Version 10.4c_5
$end
$timescale
	1ns
$end

$scope module testbench $end
$var wire 1 ! clk $end
$var wire 1 " reset $end
$var wire 1 # ns_detektor $end
$var wire 1 $ wo_detektor $end
$var wire 1 % ns_ampel [2] $end
$var wire 1 & ns_ampel [1] $end
$var wire 1 ' ns_ampel [0] $end
$var wire 1 ( wo_ampel [2] $end
$var wire 1 ) wo_ampel [1] $end
$var wire 1 * wo_ampel [0] $end

$scope module DUS $end
$var wire 1 ! clk $end
$var wire 1 " reset $end
$var wire 1 # ns_detektor $end
$var wire 1 $ wo_detektor $end
$var wire 1 % ns_ampel [2] $end
$var wire 1 & ns_ampel [1] $end
$var wire 1 ' ns_ampel [0] $end
$var wire 1 ( wo_ampel [2] $end
$var wire 1 ) wo_ampel [1] $end
$var wire 1 * wo_ampel [0] $end
$var wire 1 + timeout_start $end
$var wire 1 , timeout_ack $end
$var wire 1 - timeout $end
$var wire 1 . timeout_type [1] $end
$var wire 1 / timeout_type [0] $end
$var wire 32 0 counter $end
$upscope $end
$upscope $end
$enddefinitions $end
#0
$dumpvars
0!
0"
0#
0$
0+
0,
0-
0%
0&
0'
0(
0)
0*
0.
0/
b0 0
$end
#2500000000
1!
1"
#5000000000
0!
#7500000000
1!
1*
1'
0"
#10000000000
0!
#12500000000
1!
0'
1%
1+
1/
1.
#15000000000
0!
#17500000000
1!
b11 0
1,
1#
1$
#20000000000
0!
#22500000000
1!
0+
#25000000000
0!
#27500000000
1!
b10 0
#30000000000
0!
#32500000000
1!
b1 0
#35000000000
0!
#37500000000
1!
0,
1-
#40000000000
0!
#42500000000
1!
1)
1&
0%
#45000000000
0!
#47500000000
1!
0*
0)
1(
1'
0&
1+
0/
#50000000000
0!
#52500000000
1!
1,
0-
#55000000000
0!
#57500000000
1!
0+
#60000000000
0!
#62500000000
1!
0,
1-
#65000000000
0!
#67500000000
1!
1)
0(
1&
#70000000000
0!
#72500000000
1!
1*
0)
0'
0&
1%
1+
1/
#75000000000
0!
#77500000000
1!
b11 0
1,
0-
#80000000000
0!
#82500000000
1!
0+
#85000000000
0!
#87500000000
1!
b10 0
#90000000000
0!
#92500000000
1!
b1 0
#95000000000
0!
#97500000000
1!
0,
1-
#100000000000
0!
#102500000000
1!
1)
1&
0%
#105000000000
0!
#107500000000
1!
0*
0)
1(
1'
0&
1+
0/
#110000000000
0!
#112500000000
1!
1,
0-
#115000000000
0!
#117500000000
1!
0+
#120000000000
0!
#122500000000
1!
0,
1-
#125000000000
0!
#127500000000
1!
1)
0(
1&
#130000000000
0!
#132500000000
1!
1*
0)
0'
0&
1%
1+
1/
#135000000000
0!
#137500000000
1!
b11 0
1,
0-
#140000000000
0!
#142500000000
1!
0+
#145000000000
0!
#147500000000
1!
b10 0
#150000000000
0!
#152500000000
1!
b1 0
#155000000000
0!
#157500000000
1!
0,
1-
#160000000000
0!
#162500000000
1!
1)
1&
0%
#165000000000
0!
#167500000000
1!
0*
0)
1(
1'
0&
1+
0/
#170000000000
0!
#172500000000
1!
1,
0-
#175000000000
0!
#177500000000
1!
0+
#180000000000
0!
#182500000000
1!
0,
1-
#185000000000
0!
#187500000000
1!
1)
0(
1&
#190000000000
0!
#192500000000
1!
1*
0)
0'
0&
1%
1+
1/
#195000000000
0!
#197500000000
1!
b11 0
1,
0-
#200000000000
0!
#202500000000
1!
0+
#205000000000
0!
#207500000000
1!
b10 0
#210000000000
0!
#212500000000
1!
b1 0
#215000000000
0!
#217500000000
1!
0,
1-
#220000000000
0!
#222500000000
1!
1)
1&
0%
#225000000000
0!
#227500000000
1!
0*
0)
1(
1'
0&
1+
0/
#230000000000
0!
#232500000000
1!
1,
0-
#235000000000
0!
#237500000000
1!
0+
#240000000000
0!
#242500000000
1!
0,
1-
#245000000000
0!
#247500000000
1!
1)
0(
1&
