blatt_03/alu.vhd
entity alu is
        port(   clk: in bit;
                reset: in bit;
                opID; in bit_vector(1 downto 0);
                op1_ready: in bit;
                op2_ready: in bit;
                opID_ready: in bit;
                res_ready: out bit;
                data: inout std_logic_vector(31 downto 0)
                );
end alu;

architecture behave of alu is

signal op1, op2: signed(31 downto 0);;
signal local_opID: bit_vector(1 downto 0);
signal result: signed(31 downto 0);
signal tmp: signed(63 downto 0);

begin
cntrl: process
        begin
        wait until clk'edge and clk='1' and reset='1'; --warten auf reset
        res_ready <= 0;
        data <= (others => 'Z');

        wait until clk'edge and clk='1' and op1_ready='1'; --warten auf operand 1
        --read operand 1

        op1 <= data;

        wait until clk'edge and clk='1' and op2_ready='1'; --warten auf operand 2
        --read operand 2

        op2 <= data;

        wait until clk'edge and clk='1' and opID_ready='1'; --auf opID ready warten
        --read opID
        local_opID <= opID;
        case local_opID is
                when '00' =>
                        --addition
                        result <= op1 + op2;
                when '11' =>
                        --multiplikation
                        tmp <= op1 * op2;
                        result <= tmp(31 downto 0);
                when others =>
                        --subtraktion
                        result <= op1 - op2;
        end case;
        data <= result;
        res_ready <= '1';
        end process cntrl;
end behave;

blatt_03/testbench.vhd
LIBRARY IEEE ;
USE IEEE.std_logic_1164.all;
use IEEE.numeric_std.all;

entity testbench is
end testbench;

architecture behave of testbench is
component alu
        port(   clk: in bit;
                reset: in bit;
                opID: in bit_vector(1 downto 0);
                op1_ready: in bit;
                op2_ready: in bit;
                opID_ready: in bit;
                res_ready: out bit;
                data: inout std_logic_vector(31 downto 0));
end component;

signal reset, op1_ready, op2_ready, opID_ready, res_ready: bit;
signal opID: bit_Vector(1 downto 0);
signal data: std_logic_vector(31 downto 0);
signal result: signed(31 downto 0);
signal tmp: signed(31 downto 0);
signal clk: BIT := '0';

begin
DUS: entity work.alu PORT MAP (clk => clk, reset => reset, opID => opID, op1_ready => op1_ready, op2_ready => op2_ready, opID_ready => opID_ready, res_ready => res_ready, data => data);

clk <= NOT clk AFTER 10 ns;

stimulate: process
        begin

--
--Die Clock waits kann man bestimmt vereinfachen, aber nach 6 Stunden Fehlersuche
--habe ich da jetzt leider keinen Nerv mehr dafür, funktioniert auf jeden Fall einwandfrei
--

                --test for 8 + 4 = 12
                data <= (others => 'Z');
                wait until clk='1';
                wait until clk='0';
                reset <= '1';

                wait until clk='1';
                wait until clk='0';
                data <= std_logic_vector(to_signed(8, data'length));

                wait until clk='1';
                wait until clk='0';
                op1_ready <= '1';

                wait until clk='1';
                wait until clk='0';
                data <= std_logic_vector(to_signed(4, data'length));

                wait until clk='1';
                wait until clk='0';
                op2_ready <= '1';

                wait until clk='1';
                wait until clk='0';
                opID <= "00";
                data <= (others => 'Z');
                wait until clk='1';
                wait until clk='0';
                opID_ready <= '1';
                reset <= '0';

                wait until res_ready='1';
                wait until clk='1';
                result <= signed(data);
                wait until clk='1';
                wait until clk='0';
                assert (result=to_signed(12, data'length)) report "Test1.1 Failed!";

                --reset internal signals
                op1_ready <='0';
                op2_ready <='0';
                opID_ready <='0';

                wait until clk='1';
                wait until clk='0';

                --test for 10 + 10 = 20
                data <= (others => 'Z');
                wait until clk='1';
                wait until clk='0';
                reset <= '1';

                wait until clk='1';
                wait until clk='0';
                data <= std_logic_vector(to_signed(10, data'length));

                wait until clk='1';
                wait until clk='0';
                op1_ready <= '1';

                wait until clk='1';
                wait until clk='0';
                data <= std_logic_vector(to_signed(10, data'length));

                wait until clk='1';
                wait until clk='0';
                op2_ready <= '1';

                wait until clk='1';
                wait until clk='0';
                opID <= "00";
                data <= (others => 'Z');
                wait until clk='1';
                wait until clk='0';
                opID_ready <= '1';
                reset <= '0';

                wait until res_ready='1';
                wait until clk='1';
                result <= signed(data);
                wait until clk='1';
                wait until clk='0';
                assert (result=to_signed(20, data'length)) report "Test1.2 Failed!";

                --reset internal signals
                op1_ready <='0';
                op2_ready <='0';
                opID_ready <='0';

                wait until clk='1';
                wait until clk='0';

                --test for 8 - 4 = 4
                data <= (others => 'Z');
                wait until clk='1';
                wait until clk='0';
                reset <= '1';

                wait until clk='1';
                wait until clk='0';
                data <= std_logic_vector(to_signed(8, data'length));

                wait until clk='1';
                wait until clk='0';
                op1_ready <= '1';

                wait until clk='1';
                wait until clk='0';
                data <= std_logic_vector(to_signed(4, data'length));

                wait until clk='1';
                wait until clk='0';
                op2_ready <= '1';

                wait until clk='1';
                wait until clk='0';
                opID <= "01";
                data <= (others => 'Z');
                wait until clk='1';
                wait until clk='0';
                opID_ready <= '1';
                reset <= '0';

                wait until res_ready='1';
                wait until clk='1';
                result <= signed(data);
                wait until clk='1';
                wait until clk='0';
                assert (result=to_signed(4, data'length)) report "Test2.1 Failed!";

                --reset internal signals
                op1_ready <='0';
                op2_ready <='0';
                opID_ready <='0';

                wait until clk='1';
                wait until clk='0';


                --test for 8 - 8 = 0
                data <= (others => 'Z');
                wait until clk='1';
                wait until clk='0';
                reset <= '1';

                wait until clk='1';
                wait until clk='0';
                data <= std_logic_vector(to_signed(8, data'length));

                wait until clk='1';
                wait until clk='0';
                op1_ready <= '1';

                wait until clk='1';
                wait until clk='0';
                data <= std_logic_vector(to_signed(8, data'length));

                wait until clk='1';
                wait until clk='0';
                op2_ready <= '1';

                wait until clk='1';
                wait until clk='0';
                opID <= "01";
                data <= (others => 'Z');
                wait until clk='1';
                wait until clk='0';
                opID_ready <= '1';
                reset <= '0';

                wait until res_ready='1';
                wait until clk='1';
                result <= signed(data);
                wait until clk='1';
                wait until clk='0';
                assert (result=to_signed(0, data'length)) report "Test2.2 Failed!";

                --reset internal signals
                op1_ready <='0';
                op2_ready <='0';
                opID_ready <='0';

                wait until clk='1';
                wait until clk='0';

                --test for 8 * 4 = 32
                data <= (others => 'Z');
                wait until clk='1';
                wait until clk='0';
                reset <= '1';

                wait until clk='1';
                wait until clk='0';
                data <= std_logic_vector(to_signed(8, data'length));

                wait until clk='1';
                wait until clk='0';
                op1_ready <= '1';

                wait until clk='1';
                wait until clk='0';
                data <= std_logic_vector(to_signed(4, data'length));

                wait until clk='1';
                wait until clk='0';
                op2_ready <= '1';

                wait until clk='1';
                wait until clk='0';
                opID <= "11";
                data <= (others => 'Z');
                wait until clk='1';
                wait until clk='0';
                opID_ready <= '1';
                reset <= '0';

                wait until res_ready='1';
                wait until clk='1';
                result <= signed(data);
                wait until clk='1';
                wait until clk='0';
                assert (result=to_signed(32, data'length)) report "Test3.1 Failed!";

                --reset internal signals
                op1_ready <='0';
                op2_ready <='0';
                opID_ready <='0';

                wait until clk='1';
                wait until clk='0';


                --test for 8 * 0 = 0
                data <= (others => 'Z');
                wait until clk='1';
                wait until clk='0';
                reset <= '1';

                wait until clk='1';
                wait until clk='0';
                data <= std_logic_vector(to_signed(8, data'length));

                wait until clk='1';
                wait until clk='0';
                op1_ready <= '1';

                wait until clk='1';
                wait until clk='0';
                data <= std_logic_vector(to_signed(0, data'length));

                wait until clk='1';
                wait until clk='0';
                op2_ready <= '1';

                wait until clk='1';
                wait until clk='0';
                opID <= "11";
                data <= (others => 'Z');
                wait until clk='1';
                wait until clk='0';
                opID_ready <= '1';
                reset <= '0';

                wait until res_ready='1';
                wait until clk='1';
                result <= signed(data);
                wait until clk='1';
                wait until clk='0';
                assert (result=to_signed(0, data'length)) report "Test3.2 Failed!";

                --reset internal signals
                op1_ready <='0';
                op2_ready <='0';
                opID_ready <='0';

                wait until clk='1';
                wait until clk='0';


                wait; --testbench beenden

        end process stimulate;
end behave;

blatt_03/testbench.vcd
$date
        Mon May 29 00:43:04 2017
$end
$version
        QuestaSim Version 10.4c_5
$end
$timescale
        1ns
$end

$scope module testbench $end
$var wire 1 ! reset $end
$var wire 1 " op1_ready $end
$var wire 1 # op2_ready $end
$var wire 1 $ opID_ready $end
$var wire 1 % res_ready $end
$var wire 1 & opID [1] $end
$var wire 1 ' opID [0] $end
$var wire 1 ( data [31] $end
$var wire 1 ) data [30] $end
$var wire 1 * data [29] $end
$var wire 1 + data [28] $end
$var wire 1 , data [27] $end
$var wire 1 - data [26] $end
$var wire 1 . data [25] $end
$var wire 1 / data [24] $end
$var wire 1 0 data [23] $end
$var wire 1 1 data [22] $end
$var wire 1 2 data [21] $end
$var wire 1 3 data [20] $end
$var wire 1 4 data [19] $end
$var wire 1 5 data [18] $end
$var wire 1 6 data [17] $end
$var wire 1 7 data [16] $end
$var wire 1 8 data [15] $end
$var wire 1 9 data [14] $end
$var wire 1 : data [13] $end
$var wire 1 ; data [12] $end
$var wire 1 < data [11] $end
$var wire 1 = data [10] $end
$var wire 1 > data [9] $end
$var wire 1 ? data [8] $end
$var wire 1 @ data [7] $end
$var wire 1 A data [6] $end
$var wire 1 B data [5] $end
$var wire 1 C data [4] $end
$var wire 1 D data [3] $end
$var wire 1 E data [2] $end
$var wire 1 F data [1] $end
$var wire 1 G data [0] $end
$var wire 1 H result [31] $end
$var wire 1 I result [30] $end
$var wire 1 J result [29] $end
$var wire 1 K result [28] $end
$var wire 1 L result [27] $end
$var wire 1 M result [26] $end
$var wire 1 N result [25] $end
$var wire 1 O result [24] $end
$var wire 1 P result [23] $end
$var wire 1 Q result [22] $end
$var wire 1 R result [21] $end
$var wire 1 S result [20] $end
$var wire 1 T result [19] $end
$var wire 1 U result [18] $end
$var wire 1 V result [17] $end
$var wire 1 W result [16] $end
$var wire 1 X result [15] $end
$var wire 1 Y result [14] $end
$var wire 1 Z result [13] $end
$var wire 1 [ result [12] $end
$var wire 1 \ result [11] $end
$var wire 1 ] result [10] $end
$var wire 1 ^ result [9] $end
$var wire 1 _ result [8] $end
$var wire 1 ` result [7] $end
$var wire 1 a result [6] $end
$var wire 1 b result [5] $end
$var wire 1 c result [4] $end
$var wire 1 d result [3] $end
$var wire 1 e result [2] $end
$var wire 1 f result [1] $end
$var wire 1 g result [0] $end
$var wire 1 h tmp [31] $end
$var wire 1 i tmp [30] $end
$var wire 1 j tmp [29] $end
$var wire 1 k tmp [28] $end
$var wire 1 l tmp [27] $end
$var wire 1 m tmp [26] $end
$var wire 1 n tmp [25] $end
$var wire 1 o tmp [24] $end
$var wire 1 p tmp [23] $end
$var wire 1 q tmp [22] $end
$var wire 1 r tmp [21] $end
$var wire 1 s tmp [20] $end
$var wire 1 t tmp [19] $end
$var wire 1 u tmp [18] $end
$var wire 1 v tmp [17] $end
$var wire 1 w tmp [16] $end
$var wire 1 x tmp [15] $end
$var wire 1 y tmp [14] $end
$var wire 1 z tmp [13] $end
$var wire 1 { tmp [12] $end
$var wire 1 | tmp [11] $end
$var wire 1 } tmp [10] $end
$var wire 1 ~ tmp [9] $end
$var wire 1 !! tmp [8] $end
$var wire 1 "! tmp [7] $end
$var wire 1 #! tmp [6] $end
$var wire 1 $! tmp [5] $end
$var wire 1 %! tmp [4] $end
$var wire 1 &! tmp [3] $end
$var wire 1 '! tmp [2] $end
$var wire 1 (! tmp [1] $end
$var wire 1 )! tmp [0] $end
$var wire 1 *! clk $end
$upscope $end
$enddefinitions $end
#0
$dumpvars
0!
0"
0#
0$
0%
0*!
0&
0'
z(
z)
z*
z+
z,
z-
z.
z/
z0
z1
z2
z3
z4
z5
z6
z7
z8
z9
z:
z;
z<
z=
z>
z?
z@
zA
zB
zC
zD
zE
zF
zG
xH
xI
xJ
xK
xL
xM
xN
xO
xP
xQ
xR
xS
xT
xU
xV
xW
xX
xY
xZ
x[
x\
x]
x^
x_
x`
xa
xb
xc
xd
xe
xf
xg
xh
xi
xj
xk
xl
xm
xn
xo
xp
xq
xr
xs
xt
xu
xv
xw
xx
xy
xz
x{
x|
x}
x~
x!!
x"!
x#!
x$!
x%!
x&!
x'!
x(!
x)!
$end
#10
1*!
#20
0*!
1!
#30
1*!
#40
0*!
0G
0F
0E
1D
0C
0B
0A
0@
0?
0>
0=
0<
0;
0:
09
08
07
06
05
04
03
02
01
00
0/
0.
0-
0,
0+
0*
0)
0(
#50
1*!
#60
0*!
1"
#70
1*!
#80
0*!
1E
0D
#90
1*!
#100
0*!
1#
#110
1*!
#120
0*!
zG
zF
zE
zD
zC
zB
zA
z@
z?
z>
z=
z<
z;
z:
z9
z8
z7
z6
z5
z4
z3
z2
z1
z0
z/
z.
z-
z,
z+
z*
z)
z(
#130
1*!
#140
0*!
0!
1$
#150
1*!
#160
0*!
#170
1*!
#180
0*!
#190
1*!
0G
0F
1E
1D
0C
0B
0A
0@
0?
0>
0=
0<
0;
0:
09
08
07
06
05
04
03
02
01
00
0/
0.
0-
0,
0+
0*
0)
0(
#200
0*!
#210
1*!
1%
#220
0*!
#230
1*!
zG
zF
zE
zD
zC
zB
zA
z@
z?
z>
z=
z<
z;
z:
z9
z8
z7
z6
z5
z4
z3
z2
z1
z0
z/
z.
z-
z,
z+
z*
z)
z(
0g
0f
1e
1d
0c
0b
0a
0`
0_
0^
0]
0\
0[
0Z
0Y
0X
0W
0V
0U
0T
0S
0R
0Q
0P
0O
0N
0M
0L
0K
0J
0I
0H
#240
0*!
#250
1*!
#260
0*!
0$
0#
0"
#270
1*!
#280
0*!
#290
1*!
#300
0*!
1!
#310
1*!
0%
#320
0*!
0G
1F
0E
1D
0C
0B
0A
0@
0?
0>
0=
0<
0;
0:
09
08
07
06
05
04
03
02
01
00
0/
0.
0-
0,
0+
0*
0)
0(
#330
1*!
#340
0*!
1"
#350
1*!
#360
0*!
#370
1*!
#380
0*!
1#
#390
1*!
#400
0*!
zG
zF
zE
zD
zC
zB
zA
z@
z?
z>
z=
z<
z;
z:
z9
z8
z7
z6
z5
z4
z3
z2
z1
z0
z/
z.
z-
z,
z+
z*
z)
z(
#410
1*!
#420
0*!
0!
1$
#430
1*!
#440
0*!
#450
1*!
#460
0*!
#470
1*!
0G
0F
1E
0D
1C
0B
0A
0@
0?
0>
0=
0<
0;
0:
09
08
07
06
05
04
03
02
01
00
0/
0.
0-
0,
0+
0*
0)
0(
#480
0*!
#490
1*!
1%
#500
0*!
#510
1*!
zG
zF
zE
zD
zC
zB
zA
z@
z?
z>
z=
z<
z;
z:
z9
z8
z7
z6
z5
z4
z3
z2
z1
z0
z/
z.
z-
z,
z+
z*
z)
z(
0d
1c
#520
0*!
#530
1*!
#540
0*!
0$
0#
0"
#550
1*!
#560
0*!
#570
1*!
#580
0*!
1!
#590
1*!
0%
#600
0*!
0G
0F
0E
1D
0C
0B
0A
0@
0?
0>
0=
0<
0;
0:
09
08
07
06
05
04
03
02
01
00
0/
0.
0-
0,
0+
0*
0)
0(
#610
1*!
#620
0*!
1"
#630
1*!
#640
0*!
1E
0D
#650
1*!
#660
0*!
1#
#670
1*!
#680
0*!
zG
zF
zE
zD
zC
zB
zA
z@
z?
z>
z=
z<
z;
z:
z9
z8
z7
z6
z5
z4
z3
z2
z1
z0
z/
z.
z-
z,
z+
z*
z)
z(
1'
#690
1*!
#700
0*!
0!
1$
#710
1*!
#720
0*!
#730
1*!
#740
0*!
#750
1*!
0G
0F
1E
0D
0C
0B
0A
0@
0?
0>
0=
0<
0;
0:
09
08
07
06
05
04
03
02
01
00
0/
0.
0-
0,
0+
0*
0)
0(
#760
0*!
#770
1*!
1%
#780
0*!
#790
1*!
zG
zF
zE
zD
zC
zB
zA
z@
z?
z>
z=
z<
z;
z:
z9
z8
z7
z6
z5
z4
z3
z2
z1
z0
z/
z.
z-
z,
z+
z*
z)
z(
0c
#800
0*!
#810
1*!
#820
0*!
0$
0#
0"
#830
1*!
#840
0*!
#850
1*!
#860
0*!
1!
#870
1*!
0%
#880
0*!
0G
0F
0E
1D
0C
0B
0A
0@
0?
0>
0=
0<
0;
0:
09
08
07
06
05
04
03
02
01
00
0/
0.
0-
0,
0+
0*
0)
0(
#890
1*!
#900
0*!
1"
#910
1*!
#920
0*!
#930
1*!
#940
0*!
1#
#950
1*!
#960
0*!
zG
zF
zE
zD
zC
zB
zA
z@
z?
z>
z=
z<
z;
z:
z9
z8
z7
z6
z5
z4
z3
z2
z1
z0
z/
z.
z-
z,
z+
z*
z)
z(
#970
1*!
#980
0*!
0!
1$
#990
1*!
#1000
0*!
#1010
1*!
#1020
0*!
#1030
1*!
0G
0F
0E
0D
0C
0B
0A
0@
0?
0>
0=
0<
0;
0:
09
08
07
06
05
04
03
02
01
00
0/
0.
0-
0,
0+
0*
0)
0(
#1040
0*!
#1050
1*!
1%
#1060
0*!
#1070
1*!
zG
zF
zE
zD
zC
zB
zA
z@
z?
z>
z=
z<
z;
z:
z9
z8
z7
z6
z5
z4
z3
z2
z1
z0
z/
z.
z-
z,
z+
z*
z)
z(
0e
#1080
0*!
#1090
1*!
#1100
0*!
0$
0#
0"
#1110
1*!
#1120
0*!
#1130
1*!
#1140
0*!
1!
#1150
1*!
0%
#1160
0*!
0G
0F
0E
1D
0C
0B
0A
0@
0?
0>
0=
0<
0;
0:
09
08
07
06
05
04
03
02
01
00
0/
0.
0-
0,
0+
0*
0)
0(
#1170
1*!
#1180
0*!
1"
#1190
1*!
#1200
0*!
1E
0D
#1210
1*!
#1220
0*!
1#
#1230
1*!
#1240
0*!
zG
zF
zE
zD
zC
zB
zA
z@
z?
z>
z=
z<
z;
z:
z9
z8
z7
z6
z5
z4
z3
z2
z1
z0
z/
z.
z-
z,
z+
z*
z)
z(
1&
#1250
1*!
#1260
0*!
0!
1$
#1270
1*!
#1280
0*!
#1290
1*!
#1300
0*!
#1310
1*!
#1320
0*!
#1330
1*!
0G
0F
0E
0D
0C
1B
0A
0@
0?
0>
0=
0<
0;
0:
09
08
07
06
05
04
03
02
01
00
0/
0.
0-
0,
0+
0*
0)
0(
#1340
0*!
#1350
1*!
1%
#1360
0*!
#1370
1*!
zG
zF
zE
zD
zC
zB
zA
z@
z?
z>
z=
z<
z;
z:
z9
z8
z7
z6
z5
z4
z3
z2
z1
z0
z/
z.
z-
z,
z+
z*
z)
z(
1b
#1380
0*!
#1390
1*!
#1400
0*!
0$
0#
0"
#1410
1*!
#1420
0*!
#1430
1*!
#1440
0*!
1!
#1450
1*!
0%
#1460
0*!
0G
0F
0E
1D
0C
0B
0A
0@
0?
0>
0=
0<
0;
0:
09
08
07
06
05
04
03
02
01
00
0/
0.
0-
0,
0+
0*
0)
0(
#1470
1*!
#1480
0*!
1"
#1490
1*!
#1500
0*!
0D
#1510
1*!
#1520
0*!
1#
#1530
1*!
#1540
0*!
zG
zF
zE
zD
zC
zB
zA
z@
z?
z>
z=
z<
z;
z:
z9
z8
z7
z6
z5
z4
z3
z2
z1
z0
z/
z.
z-
z,
z+
z*
z)
z(
#1550
1*!
#1560
0*!
0!
1$
#1570
1*!
#1580
0*!
#1590
1*!
#1600
0*!
#1610
1*!
#1620
0*!
#1630
1*!
0G
0F
0E
0D
0C
0B
0A
0@
0?
0>
0=
0<
0;
0:
09
08
07
06
05
04
03
02
01
00
0/
0.
0-
0,
0+
0*
0)
0(
#1640
0*!
#1650
1*!
1%
#1660
0*!
#1670
1*!
zG
zF
zE
zD
zC
zB
zA
z@
z?
z>
z=
z<
z;
z:
z9
z8
z7
z6
z5
z4
z3
z2
z1
z0
z/
z.
z-
z,
z+
z*
z)
z(
0b
#1680
0*!
#1690
1*!
#1700
0*!
0$
0#
0"
