blatt_05/ohne Timer/ampel.vhd
entity ampel is
	port(clk, reset, ns_detektor, wo_detektor: in bit;
		ns_ampel, wo_ampel: out bit_vector(2 downto 0));
end ampel;



architecture behave of ampel is


--ns_g -> nord-sued ist gruen
--ns_r -> nord-sued ist rot
--ns_ry -> nord-sued ist rot-gelb
--ns_y -> nord-sued ist gelb
--entsprechende Benennung fuer wo
type T_STATE is (s_off, s_ns_r_wo_r, s_ns_g_wo_r, s_ns_y_wo_ry, s_ns_r_wo_g, s_ns_ry_wo_y);
signal NEXT_STATE : T_STATE;
signal STATE: T_STATE := s_off;

begin 

fsm:	process(STATE, clk)
	begin
	
	if clk'event and clk='1' then
		if reset = '1' then
			NEXT_STATE <= s_ns_r_wo_r;
			ns_ampel <= "001";
			wo_ampel <= "001";
		else

case STATE is
	when s_off =>
	when s_ns_r_wo_r =>
		NEXT_STATE <= s_ns_g_wo_r;
		ns_ampel <= "100";
		wo_ampel <= "001";	
	when s_ns_g_wo_r =>
		if wo_detektor = '1' then
			NEXT_STATE <= s_ns_y_wo_ry;
			ns_ampel <= "010";
			wo_ampel <= "011";
		end if;
	when s_ns_y_wo_ry =>
		NEXT_STATE <= s_ns_r_wo_g;
		ns_ampel <= "001";
		wo_ampel <= "100";
	when s_ns_r_wo_g =>
		if ns_detektor = '1' then
			NEXT_STATE <= s_ns_ry_wo_y;
			ns_ampel <= "011";
			wo_ampel <= "010";
		end if;
	when s_ns_ry_wo_y =>
		NEXT_STATE <= s_ns_g_wo_r;
		ns_ampel <= "100";
		wo_ampel <= "001";
end case;
		end if;
	end if;		
end process fsm;

REG: 	process(clk)
	begin
	--state an fallender taktflanke aendern, damit ein Zustandswechsel keine 2 Takte braucht
	if clk'event and clk='0' then
		STATE <= NEXT_STATE;
	end if;
end process REG;
		

end behave;

blatt_05/ohne Timer/testbench.vhd
entity testbench is
end testbench;

architecture behave of testbench is
component ampel is
	port(clk, reset, ns_detektor, wo_detektor: in bit;
        	ns_ampel, wo_ampel: out bit_vector(2 downto 0));
end component;

signal clk, reset, ns_detektor, wo_detektor: bit := '0';
signal ns_ampel, wo_ampel: bit_vector(2 downto 0);


begin

DUS: entity work.ampel port map (clk, reset, ns_detektor, wo_detektor, ns_ampel, wo_ampel);

clk <= NOT clk after 2500 ms;

stimulate : process
	begin
	wait until clk'event and clk='1';
	reset <= '1';
	wait until clk'event and clk='1';
	reset <= '0';
	wait for 10 sec;
	wait until clk'event and clk='1';
	wo_detektor <= '1';
	wait until clk'event and clk='1';
	wait for 20 sec;
	wo_detektor <= '0';
	wait until clk'event and clk='1';
	ns_detektor <= '1';
	wait until clk'event and clk='1';
	wait for 20 sec;
	ns_detektor <= '0';
	wait until clk'event and clk='1';
	wo_detektor <= '1';
        wait until clk'event and clk='1';
        wait for 20 sec;
        wo_detektor <= '0';
        wait until clk'event and clk='1';
	ns_detektor <= '1';
        wait until clk'event and clk='1';
        wait for 20 sec;

        ns_detektor <= '0';
	wait;	

end process stimulate;

end behave;

blatt_05/ohne Timer/testbench.vcd
$date
	Fri Jun 16 18:18:36 2017
$end
$version
	QuestaSim Version 10.4c_5
$end
$timescale
	1ns
$end

$scope module testbench $end
$var wire 1 ! clk $end
$var wire 1 " reset $end
$var wire 1 # ns_detektor $end
$var wire 1 $ wo_detektor $end
$var wire 1 % ns_ampel [2] $end
$var wire 1 & ns_ampel [1] $end
$var wire 1 ' ns_ampel [0] $end
$var wire 1 ( wo_ampel [2] $end
$var wire 1 ) wo_ampel [1] $end
$var wire 1 * wo_ampel [0] $end
$upscope $end
$enddefinitions $end
#0
$dumpvars
0!
0"
0#
0$
0%
0&
0'
0(
0)
0*
$end
#2500000000
1!
1"
#5000000000
0!
#7500000000
1!
1*
1'
0"
#10000000000
0!
#12500000000
1!
0'
1%
#15000000000
0!
#17500000000
1!
#20000000000
0!
#22500000000
1!
1$
#25000000000
0!
#27500000000
1!
1)
1&
0%
#30000000000
0!
#32500000000
1!
0*
0)
1(
1'
0&
#35000000000
0!
#37500000000
1!
#40000000000
0!
#42500000000
1!
#45000000000
0!
#47500000000
1!
0$
#50000000000
0!
#52500000000
1!
1#
#55000000000
0!
#57500000000
1!
1)
0(
1&
#60000000000
0!
#62500000000
1!
1*
0)
0'
0&
1%
#65000000000
0!
#67500000000
1!
#70000000000
0!
#72500000000
1!
#75000000000
0!
#77500000000
1!
0#
#80000000000
0!
#82500000000
1!
1$
#85000000000
0!
#87500000000
1!
1)
1&
0%
#90000000000
0!
#92500000000
1!
0*
0)
1(
1'
0&
#95000000000
0!
#97500000000
1!
#100000000000
0!
#102500000000
1!
#105000000000
0!
#107500000000
1!
0$
#110000000000
0!
#112500000000
1!
1#
#115000000000
0!
#117500000000
1!
1)
0(
1&
#120000000000
0!
#122500000000
1!
1*
0)
0'
0&
1%
#125000000000
0!
#127500000000
1!
#130000000000
0!
#132500000000
1!
#135000000000
0!
#137500000000
1!
0#
