blatt_02/fulladder.vhd
ENTITY fulladder IS
PORT (  A, B, C_in : IN BIT ;
        S , C : OUT BIT ) ;
END fulladder;

ARCHITECTURE behave OF fulladder IS
BEGIN
        S <= A xor B xor C_in after 1ns;
        C <= (A and B) or (C_in and A) or (C_in and B) after 1ns;
END behave;

blatt_02/ripplecarry.vhd
ENTITY ripplecarry IS
        GENERIC (N: positive := 8);
        PORT(   A,B: IN BIT_VECTOR(N-1 DOWNTO 0);
                C_in: IN BIT;
                S: OUT BIT_VECTOR(N-1 DOWNTO 0);
                C_out: OUT BIT);
END ripplecarry;


ARCHITECTURE behave OF ripplecarry IS
COMPONENT fulladder
        PORT(   A,B, C_in: IN BIT;
                S, C: OUT BIT);
END COMPONENT;
SIGNAL sig: BIT_VECTOR(N DOWNTO 0);

BEGIN
        sig(0) <= C_in;

        FA: FOR i IN 0 TO N-1 GENERATE
                F1: fulladder PORT MAP(A(i), B(i), sig(i), S(i), sig(i+1));
        END GENERATE;
        C_out <= sig(N);
END;

blatt_02/testbench.vhd
ENTITY testbench IS
END testbench;

ARCHITECTURE behavior OF testbench IS
        COMPONENT ripplecarry
                GENERIC(N: positive := 16);
                PORT(   A,B: IN BIT_VECTOR(N-1 DOWNTO 0);
                        C_in: IN BIT;
                        S: OUT BIT_VECTOR(N-1 DOWNTO 0);
                        C_out: OUT BIT);
        END COMPONENT;
        signal x,y, sum: BIT_VECTOR(15 DOWNTO 0);
        signal c_out: BIT;
        signal c_in : bit;
BEGIN
        UUT: entity work.ripplecarry GENERIC MAP (N => 16) PORT MAP(x,y,c_in, sum, c_out);
        tb: process
                begin
                        x <= "0000000000000001";
                        y <= "0000000000000001";
                        c_in <= '0';
                        wait for 25ns;
                        x <= "0000000000000010";
                        y <= "0000000000000010";
                        c_in <= '0';
                        wait for 25ns;
                        x <= "0000000000000000";
                        y <= "0000000000000100";
                        c_in <= '0';
                        wait for 25ns;
                        x <= "0000000000000000";
                        y <= "0000000000000000";
                        c_in <= '0';
                        wait for 25ns;
                        x <= "1111111111111111";
                        y <= "0000000000000000";
                        c_in <= '1';
                        wait for 25ns;
                        x <= "1111111111111111";
                        y <= "0000000000000001";
                        c_in <= '0';
                        wait for 25ns;
                        wait;
                end process tb;
END;

blatt_02/testbench.vcd
$date
        Sun May 21 23:39:04 2017
$end
$version
        QuestaSim Version 10.4c_5
$end
$timescale
        1ns
$end

$scope module testbench $end
$var wire 1 ! x [15] $end
$var wire 1 " x [14] $end
$var wire 1 # x [13] $end
$var wire 1 $ x [12] $end
$var wire 1 % x [11] $end
$var wire 1 & x [10] $end
$var wire 1 ' x [9] $end
$var wire 1 ( x [8] $end
$var wire 1 ) x [7] $end
$var wire 1 * x [6] $end
$var wire 1 + x [5] $end
$var wire 1 , x [4] $end
$var wire 1 - x [3] $end
$var wire 1 . x [2] $end
$var wire 1 / x [1] $end
$var wire 1 0 x [0] $end
$var wire 1 1 y [15] $end
$var wire 1 2 y [14] $end
$var wire 1 3 y [13] $end
$var wire 1 4 y [12] $end
$var wire 1 5 y [11] $end
$var wire 1 6 y [10] $end
$var wire 1 7 y [9] $end
$var wire 1 8 y [8] $end
$var wire 1 9 y [7] $end
$var wire 1 : y [6] $end
$var wire 1 ; y [5] $end
$var wire 1 < y [4] $end
$var wire 1 = y [3] $end
$var wire 1 > y [2] $end
$var wire 1 ? y [1] $end
$var wire 1 @ y [0] $end
$var wire 1 A sum [15] $end
$var wire 1 B sum [14] $end
$var wire 1 C sum [13] $end
$var wire 1 D sum [12] $end
$var wire 1 E sum [11] $end
$var wire 1 F sum [10] $end
$var wire 1 G sum [9] $end
$var wire 1 H sum [8] $end
$var wire 1 I sum [7] $end
$var wire 1 J sum [6] $end
$var wire 1 K sum [5] $end
$var wire 1 L sum [4] $end
$var wire 1 M sum [3] $end
$var wire 1 N sum [2] $end
$var wire 1 O sum [1] $end
$var wire 1 P sum [0] $end
$var wire 1 Q c_out $end
$var wire 1 R c_in $end
$upscope $end
$enddefinitions $end
#0
$dumpvars
0Q
0R
0!
0"
0#
0$
0%
0&
0'
0(
0)
0*
0+
0,
0-
0.
0/
10
01
02
03
04
05
06
07
08
09
0:
0;
0<
0=
0>
0?
1@
0A
0B
0C
0D
0E
0F
0G
0H
0I
0J
0K
0L
0M
0N
0O
0P
$end
#2
1O
#25
0@
1?
00
1/
#27
0O
1N
#50
0?
1>
0/
#51
0N
#52
1N
1M
#53
0M
#75
0>
#76
0N
#100
1R
10
1/
1.
1-
1,
1+
1*
1)
1(
1'
1&
1%
1$
1#
1"
1!
#101
1A
1B
1C
1D
1E
1F
1G
1H
1I
1J
1K
1L
1M
1N
1O
#102
0O
#103
0N
#104
0M
#105
0L
#106
0K
#107
0J
#108
0I
#109
0H
#110
0G
#111
0F
#112
0E
#113
0D
#114
0C
#115
0B
#116
0A
1Q
#125
0R
1@
#200
0!
0"
0#
0$
0%
0&
0'
0(
0)
0*
0+
0,
0-
0.
0/
00
0@
#201
1O
1N
1M
1L
1K
1J
1I
1H
1G
1F
1E
1D
1C
1B
1A
0Q
#202
0A
0B
0C
0D
0E
0F
0G
0H
0I
0J
0K
0L
0M
0N
0O
