blatt_07/alu.vhd
LIBRARY IEEE;
USE IEEE.STD_LOGIC_ARITH.ALL;
USE IEEE.std_logic_1164.ALL;

ENTITY ALU_ENTITY IS
	PORT(CLK, RESET : IN STD_LOGIC;
		IN0,IN1 : IN STD_LOGIC_VECTOR(31 DOWNTO 0);
		OP: IN STD_LOGIC_VECTOR(2 DOWNTO 0);
		RESULT: OUT STD_LOGIC_VECTOR(31 DOWNTO 0));
END ENTITY;

ARCHITECTURE ALU_ARCH OF ALU_ENTITY IS
BEGIN
    PROCESS(CLK) 
    VARIABLE TMP : STD_LOGIC_VECTOR(63 DOWNTO 0);
    BEGIN
		IF RISING_EDGE(CLK) THEN
			IF RESET = '1' THEN
				 RESULT <= (OTHERS => '0');
			ELSE
				 CASE(OP) IS
					WHEN "000" => RESULT <= UNSIGNED(IN0) + UNSIGNED(IN1);
					WHEN "001" => RESULT <= UNSIGNED(IN0) - UNSIGNED(IN1);
					WHEN "010" => 
						TMP := UNSIGNED(IN0) * UNSIGNED(IN1);
						RESULT <= TMP(31 DOWNTO 0);
					WHEN "011" => RESULT <= IN0 AND IN1;
					WHEN "100" => RESULT <= IN0 OR IN1;
					WHEN "101" => RESULT <= IN0 XOR IN1;
					WHEN OTHERS => RESULT <= (OTHERS => '0');
				 END CASE;
			END IF;
		END IF;
	END PROCESS;
END ARCHITECTURE;

blatt_07/2_a_testbench.vhd
LIBRARY IEEE;
USE IEEE.STD_LOGIC_ARITH.ALL;
USE IEEE.std_logic_1164.ALL;

entity testbench is
end testbench;

architecture behave of testbench is
component alu is
	PORT(CLK, RESET : IN STD_LOGIC;
		IN0,IN1 : IN STD_LOGIC_VECTOR(31 DOWNTO 0);
		OP: IN STD_LOGIC_VECTOR(2 DOWNTO 0);
		RESULT: OUT STD_LOGIC_VECTOR(31 DOWNTO 0));
end component;

signal CLK: std_logic := '0';
signal RESET: std_logic;
signal IN0,IN1: std_logic_vector(31 downto 0);
signal OP: std_logic_vector(2 downto 0);
signal RESULT: std_logic_vector(31 downto 0);


begin

CLK <= not CLK after 250 ps;
DUS: entity work.ALU_ENTITY port map (CLK, RESET, IN0, IN1, OP, RESULT);

stimulate: process
	begin
	wait until clk'event and clk='1';
	RESET <= '1';
	wait until clk'event and clk='1';
	RESET <= '0';
	
	IN0 <= x"1234f001";
	IN1 <= x"93ca123f";
	OP <= "000";

	wait until clk'event and clk='1';
	IN0 <= x"12345678";
	IN1 <= x"45891000";
	OP <= "100";

	wait until clk'event and clk='1';
	
	IN0 <= x"89ad1755";
	IN1 <= x"88899912";
	OP <= "011";

	wait until clk'event and clk='1';
	
	IN0 <= x"11123456";
	IN1 <= x"10000000";
	OP <= "010";

	
	wait until clk'event and clk='1';

	IN0 <= x"01234567";
	IN1 <= x"00001001";
	OP <= "001";

	wait until clk'event and clk='1';
	RESET <= '1';
	IN0 <= x"00000000";
	IN1 <= x"00000000";
	OP <= "000";

	wait until clk'event and clk='1';
	RESET <= '0';
	wait;	
	


end process stimulate;
end behave;

blatt_07/2_f_testbench_timing.vcd
$date
	Sat Jul  1 16:43:12 2017
$end
$version
	QuestaSim Version 10.4c_5
$end
$timescale
	1ps
$end

$scope module testbench $end
$var wire 1 ! CLK $end
$var wire 1 " RESET $end
$var wire 1 # IN0 [31] $end
$var wire 1 $ IN0 [30] $end
$var wire 1 % IN0 [29] $end
$var wire 1 & IN0 [28] $end
$var wire 1 ' IN0 [27] $end
$var wire 1 ( IN0 [26] $end
$var wire 1 ) IN0 [25] $end
$var wire 1 * IN0 [24] $end
$var wire 1 + IN0 [23] $end
$var wire 1 , IN0 [22] $end
$var wire 1 - IN0 [21] $end
$var wire 1 . IN0 [20] $end
$var wire 1 / IN0 [19] $end
$var wire 1 0 IN0 [18] $end
$var wire 1 1 IN0 [17] $end
$var wire 1 2 IN0 [16] $end
$var wire 1 3 IN0 [15] $end
$var wire 1 4 IN0 [14] $end
$var wire 1 5 IN0 [13] $end
$var wire 1 6 IN0 [12] $end
$var wire 1 7 IN0 [11] $end
$var wire 1 8 IN0 [10] $end
$var wire 1 9 IN0 [9] $end
$var wire 1 : IN0 [8] $end
$var wire 1 ; IN0 [7] $end
$var wire 1 < IN0 [6] $end
$var wire 1 = IN0 [5] $end
$var wire 1 > IN0 [4] $end
$var wire 1 ? IN0 [3] $end
$var wire 1 @ IN0 [2] $end
$var wire 1 A IN0 [1] $end
$var wire 1 B IN0 [0] $end
$var wire 1 C IN1 [31] $end
$var wire 1 D IN1 [30] $end
$var wire 1 E IN1 [29] $end
$var wire 1 F IN1 [28] $end
$var wire 1 G IN1 [27] $end
$var wire 1 H IN1 [26] $end
$var wire 1 I IN1 [25] $end
$var wire 1 J IN1 [24] $end
$var wire 1 K IN1 [23] $end
$var wire 1 L IN1 [22] $end
$var wire 1 M IN1 [21] $end
$var wire 1 N IN1 [20] $end
$var wire 1 O IN1 [19] $end
$var wire 1 P IN1 [18] $end
$var wire 1 Q IN1 [17] $end
$var wire 1 R IN1 [16] $end
$var wire 1 S IN1 [15] $end
$var wire 1 T IN1 [14] $end
$var wire 1 U IN1 [13] $end
$var wire 1 V IN1 [12] $end
$var wire 1 W IN1 [11] $end
$var wire 1 X IN1 [10] $end
$var wire 1 Y IN1 [9] $end
$var wire 1 Z IN1 [8] $end
$var wire 1 [ IN1 [7] $end
$var wire 1 \ IN1 [6] $end
$var wire 1 ] IN1 [5] $end
$var wire 1 ^ IN1 [4] $end
$var wire 1 _ IN1 [3] $end
$var wire 1 ` IN1 [2] $end
$var wire 1 a IN1 [1] $end
$var wire 1 b IN1 [0] $end
$var wire 1 c OP [2] $end
$var wire 1 d OP [1] $end
$var wire 1 e OP [0] $end
$var wire 1 f RESULT [31] $end
$var wire 1 g RESULT [30] $end
$var wire 1 h RESULT [29] $end
$var wire 1 i RESULT [28] $end
$var wire 1 j RESULT [27] $end
$var wire 1 k RESULT [26] $end
$var wire 1 l RESULT [25] $end
$var wire 1 m RESULT [24] $end
$var wire 1 n RESULT [23] $end
$var wire 1 o RESULT [22] $end
$var wire 1 p RESULT [21] $end
$var wire 1 q RESULT [20] $end
$var wire 1 r RESULT [19] $end
$var wire 1 s RESULT [18] $end
$var wire 1 t RESULT [17] $end
$var wire 1 u RESULT [16] $end
$var wire 1 v RESULT [15] $end
$var wire 1 w RESULT [14] $end
$var wire 1 x RESULT [13] $end
$var wire 1 y RESULT [12] $end
$var wire 1 z RESULT [11] $end
$var wire 1 { RESULT [10] $end
$var wire 1 | RESULT [9] $end
$var wire 1 } RESULT [8] $end
$var wire 1 ~ RESULT [7] $end
$var wire 1 !! RESULT [6] $end
$var wire 1 "! RESULT [5] $end
$var wire 1 #! RESULT [4] $end
$var wire 1 $! RESULT [3] $end
$var wire 1 %! RESULT [2] $end
$var wire 1 &! RESULT [1] $end
$var wire 1 '! RESULT [0] $end
$upscope $end
$enddefinitions $end
#0
$dumpvars
0!
x"
x#
x$
x%
x&
x'
x(
x)
x*
x+
x,
x-
x.
x/
x0
x1
x2
x3
x4
x5
x6
x7
x8
x9
x:
x;
x<
x=
x>
x?
x@
xA
xB
xC
xD
xE
xF
xG
xH
xI
xJ
xK
xL
xM
xN
xO
xP
xQ
xR
xS
xT
xU
xV
xW
xX
xY
xZ
x[
x\
x]
x^
x_
x`
xa
xb
xc
xd
xe
xf
xg
xh
xi
xj
xk
xl
xm
xn
xo
xp
xq
xr
xs
xt
xu
xv
xw
xx
xy
xz
x{
x|
x}
x~
x!!
x"!
x#!
x$!
x%!
x&!
x'!
$end
#250
1!
1"
#500
0!
#750
1!
0e
0d
0c
1b
1a
1`
1_
1^
1]
0\
0[
0Z
1Y
0X
0W
1V
0U
0T
0S
0R
1Q
0P
1O
0N
0M
1L
1K
1J
1I
0H
0G
1F
0E
0D
1C
1B
0A
0@
0?
0>
0=
0<
0;
0:
09
08
07
16
15
14
13
02
01
10
0/
1.
1-
0,
0+
0*
1)
0(
0'
1&
0%
0$
0#
0"
#850
0f
0g
0h
0i
0j
0k
0l
0m
0n
0o
0p
0q
0r
0s
0t
0u
0v
0w
0x
0y
0z
0{
0|
0}
0~
0!!
0"!
0#!
0$!
0%!
0&!
0'!
#1000
0!
#1250
1!
1c
0b
0a
0`
0_
0^
0]
0Y
1R
0Q
0L
0I
1H
0F
1D
0C
0B
1?
1>
1=
1<
19
18
05
03
x~
x{
x}
xz
x&!
xx
xw
xg
xj
x%!
#1350
1f
1h
xi
1k
xl
xm
xn
xo
xp
xq
xr
1t
xu
xv
xy
1|
x!!
x"!
x#!
x$!
x'!
xs
#1500
0!
#1750
1!
1e
1d
0c
1a
1^
1Z
1W
1S
0J
0H
1G
0D
1C
1B
1@
0?
0=
1:
04
12
1/
0.
1+
1*
0)
1'
0&
1#
xk
x|
#1850
0f
1g
0h
0j
0o
1r
0t
0v
0x
0z
0}
0~
0%!
0&!
0'!
#2000
0!
#2250
1!
0e
0a
0^
0Z
0W
0V
0S
0R
0O
0K
0G
1F
0C
0B
1A
0:
09
15
02
11
00
0/
1.
0-
0+
0'
1&
0#
x}
xj
xv
xz
xf
x%!
x&!
x'!
#2350
0g
0i
0k
0l
0q
0w
0"!
0$!
xr
#2500
0!
#2750
1!
1e
0d
1b
1V
0F
1B
0>
1=
1:
06
05
14
12
0.
1-
0&
xx
#2850
xg
xh
1i
xk
xl
xo
xq
xt
0v
1y
1|
1~
1"!
1#!
1$!
0%!
1&!
0'!
xw
#3000
0!
#3250
1!
0e
0b
0V
0B
0A
0@
0=
0<
0:
08
04
02
01
0-
0*
1"
x"!
x&!
xy
#3350
0f
0h
0i
0j
0k
0l
0n
0o
0q
0r
0s
0z
0|
0~
0#!
0$!
x%!
#3500
0!
#3750
1!
0"
#3850
0m
0p
0t
0u
0g
0w
0x
0y
0{
0}
0!!
0"!
0%!
0&!
