blatt_04/waschmaschine.vhd
entity waschmaschine is
	port(clk, reset, start, abbruch, tuere_zu, wasser_ok, temp_ok,
	     waschen_ok, spuelen_ok, pumpen_taste, pumpen_ok, schleuder_taste,
	     schleudern_ok: IN BIT;
	     
             wasser_auf, heizen, waschen, spuelen, pumpen, schleudern: OUT BIT);
end waschmaschine;

architecture behave of waschmaschine is
type T_STATE is (s_ruhezustand, s_wasser_einlassen, s_heizen, s_waschen, s_spuelen, s_pumpen, s_schleudern,
		 s_abbruch, s_wasser_abpumpen);
signal NEXT_STATE : T_STATE;
signal STATE : T_STATE := s_ruhezustand;

begin

fsm: 	process(STATE, clk)
	begin
	if clk'event and clk='1' then
		if reset = '1' then --reset Taste wurde gedrückt, alles zurücksetzen und in Ruhezustand wechseln
                        wasser_auf <= '0';
	                heizen <= '0';
                        waschen <= '0';
                        spuelen <= '0';
                        pumpen <= '0';
                        schleudern <= '0';
                        NEXT_STATE <= s_ruhezustand;                        
		else	
			case STATE is
				when s_ruhezustand =>
					if (start = '1' and tuere_zu = '1') then
						wasser_auf <= '1';
						NEXT_STATE <= s_wasser_einlassen;
					end if;
				when s_wasser_einlassen =>
					if (abbruch = '1') then --falls abbruch gedrückt  wechsle in Abbruchzustand
						NEXT_STATE <= s_abbruch;
					else
						if (wasser_ok = '1') then
							wasser_auf <= '0';
							heizen <= '1';
							NEXT_STATE <= s_heizen;
						end if;
					end if;
				when s_heizen =>
					if (abbruch = '1') then --falls abbruch gedrückt  wechsle in Abbruchzustand
                                                NEXT_STATE <= s_abbruch;
                                        else
						if (temp_ok = '1') then
							heizen <= '0';
							waschen <= '1';
							NEXT_STATE <= s_waschen;
						end if;
					end if;
				when s_waschen =>
					if (abbruch = '1') then --falls abbruch gedrückt  wechsle in Abbruchzustand
                                                NEXT_STATE <= s_abbruch;
                                        else
						if (waschen_ok = '1') then
                        				waschen <= '0';
							spuelen <= '1';
							NEXT_STATE <= s_spuelen;
						end if;		
                			end if;
				when s_spuelen =>
					if (abbruch = '1') then --falls abbruch gedrückt  wechsle in Abbruchzustand
                                                NEXT_STATE <= s_abbruch;
                                        else
                                                if (spuelen_ok = '1') then
							if (pumpen_taste = '1') then
								pumpen <= '1';
								spuelen <= '0';
								NEXT_STATE <= s_pumpen;
							else
								spuelen <= '0';
								NEXT_STATE <= s_ruhezustand; --fertig
							end if;
						end if;
					end if;
                		when s_pumpen =>
					if (abbruch = '1') then --falls abbruch gedrückt  wechsle in Abbruchzustand
                                                NEXT_STATE <= s_abbruch;
                                        else   
						if (pumpen_ok = '1') then
							if (schleuder_taste = '1') then
								pumpen <= '0';
								schleudern <= '1';
								NEXT_STATE <= s_schleudern;
							else
								pumpen <= '0';
	        		        	        	NEXT_STATE <= s_ruhezustand; --fertig
							end if;
						end if;
					end if;
		                when s_schleudern =>
					if (abbruch = '1') then --falls abbruch gedrückt  wechsle in Abbruchzustand
                                                NEXT_STATE <= s_abbruch;
                                        else 
						if (schleudern_ok = '1') then
							schleudern <= '0';			
		                        		NEXT_STATE <= s_ruhezustand;
						end if;
					end if;
		                when s_abbruch =>
					--setze signale zurück und beginne Abpumpen
 					wasser_auf <= '0';
                                        heizen <= '0';
                                        waschen <= '0';
                                        spuelen <= '0';
                                        schleudern <= '0';

					if (pumpen_ok = '1') then --kein Wasser in der Maschine
						NEXT_STATE <= s_ruhezustand;
					else
						pumpen <= '1';
			                      	NEXT_STATE <= s_wasser_abpumpen;
					end if;
				when s_wasser_abpumpen =>
					if (pumpen_ok = '1') then --pumpen bis kein Wasser mehr in der Maschine ist
                        			pumpen <= '0';
						NEXT_STATE <= s_abbruch;
					end if;
			end case;
		end if;
	end if;
	end process fsm;

REG: 	process(clk)
	begin
		if clk'event and clk = '1' then
			STATE <= NEXT_STATE;
		end if;
	end process REG;

end behave;

blatt_04/testbench.vhd
entity testbench is
end testbench;

architecture behave of testbench is
component waschmaschine
	port(clk, reset, start, abbruch, tuere_zu, wasser_ok, temp_ok,
             waschen_ok, spuelen_ok, pumpen_taste, pumpen_ok, schleuder_taste,
             schleudern_ok: IN BIT;

             wasser_auf, heizen, waschen, spuelen, pumpen, schleudern: OUT BIT);
end component;

signal clk, reset, start, abbruch, tuere_zu, wasser_ok, temp_ok,
       waschen_ok, spuelen_ok, pumpen_taste, pumpen_ok, schleuder_taste,
       schleudern_ok : BIT := '0';

signal wasser_auf, heizen, waschen, spuelen, pumpen, schleudern : BIT := '0';

begin

DUS: entity work.waschmaschine PORT MAP(clk, reset, start, abbruch, tuere_zu, wasser_ok, temp_ok, 
				waschen_ok, spuelen_ok, pumpen_taste, pumpen_ok, schleuder_taste,
             			schleudern_ok,
             			wasser_auf, heizen, waschen, spuelen, pumpen, schleudern);

clk <= NOT clk AFTER 1 ns;

stimulate: 	process
		begin		
                	wait until clk'event and clk='1'; --starte Stimulation bei steigender Flanke
			tuere_zu <= '1'; --mache die Tuere zu
			pumpen_taste <= '0'; --betätige die Pumpentaste nicht
			schleuder_taste <= '0'; --betätige die Schleuderntaste nicht
			wait until clk'event and clk='1'; --warte bis zur nächsten Taktflanke
			start <= '1'; --starte den Waschgang
			wait until wasser_auf = '1'; --warte bis die Maschine beginnt sich mit Wasser zu fuellen
			wait until clk'event and clk='1'; --und dann bis zur nächsten Flanke
			wasser_ok <= '1'; --singalisiere, dass die Waschmaschine mit Wasser gefuellt ist (simuliert Sendsor)
			start <= '0'; --lasse den Startknopf wieder los	
			wait until heizen = '1'; --warte bis die Maschine beginnt zu heizen
			wait until clk'event and clk = '1'; --und dann bis zur nächsten Flanke
			wasser_ok <= '0'; --zurücksetzen des Sensorwertes
			temp_ok <= '1'; --signalisiere, dass das Wasser warm genug ist
			wait until waschen = '1'; --warte bis die Maschine beginnt zu waschen
			wait until clk'event and clk = '1'; --und dann bis zur nächsten Flanke
			temp_ok <= '0'; --zurücksetzen des Sensorwertes
			waschen_ok <= '1'; --signalisiere, dass das Waschen abgeschlossen ist
			wait until spuelen = '1'; --warte bis die Maschine beginnt zu spuelen
                        wait until clk'event and clk = '1'; --und dann bis zur nächsten Flanke
			waschen_ok <= '0'; --zurücksetzen des Sensorwertes
			spuelen_ok <= '1'; --singalisiere, dass das Spuelen abgeschlpssen ist 

			wait until spuelen = '0'; --warte bis die Maschine fertig ist mit spuelen 
                        wait until clk'event and clk = '1'; --und dann bis zur nächsten Flanke
			spuelen_ok <= '0'; --zurücksetzen des Sensorwertes
			tuere_zu <= '0'; --öffne die Türe
		
			wait for 10 ns; --warte bis zum nächsten Start	

			wait until clk'event and clk='1'; --starte Stimulation bei steigender Flanke
                        tuere_zu <= '1'; --mache die Tuere zu
                        pumpen_taste <= '0'; --betätige die Pumpentaste nicht
                        schleuder_taste <= '0'; --betätige die Schleuderntaste nicht
                        wait until clk'event and clk='1'; --warte bis zur nächsten Taktflanke
                        start <= '1'; --starte den Waschgang
                        wait until wasser_auf = '1'; --warte bis die Maschine beginnt sich mit Wasser zu fuellen
                        wait until clk'event and clk='1'; --und dann bis zur nächsten Flanke
                        wasser_ok <= '1'; --singalisiere, dass die Waschmaschine mit Wasser gefuellt ist (simuliert Sendsor)
                        start <= '0'; --lasse den Startknopf wieder los
                        wait until heizen = '1'; --warte bis die Maschine beginnt zu heizen
                        wait until clk'event and clk = '1'; --und dann bis zur nächsten Flanke
                        wasser_ok <= '0'; --zurücksetzen des Sensorwertes
			
			reset <= '1'; --gebe das Reset Signal
			
			wait for 6 ns; --warte kurz
			reset <= '0'; --setze das Reset Signal zurück
			tuere_zu <= '0'; --öffne die Türe
			
			
			wait for 10 ns; --warte bis zum nächsten Start

			wait until clk'event and clk='1'; --starte Stimulation bei steigender Flanke
                        tuere_zu <= '1'; --mache die Tuere zu
                        pumpen_taste <= '0'; --betätige die Pumpentaste nicht
                        schleuder_taste <= '0'; --betätige die Schleuderntaste nicht
                        wait until clk'event and clk='1'; --warte bis zur nächsten Taktflanke
                        start <= '1'; --starte den Waschgang
                        wait until wasser_auf = '1'; --warte bis die Maschine beginnt sich mit Wasser zu fuellen
                        wait until clk'event and clk='1'; --und dann bis zur nächsten Flanke
                        wasser_ok <= '1'; --singalisiere, dass die Waschmaschine mit Wasser gefuellt ist (simuliert Sendsor)
                        start <= '0'; --lasse den Startknopf wieder los
                        wait until heizen = '1'; --warte bis die Maschine beginnt zu heizen
                        wait until clk'event and clk = '1'; --und dann bis zur nächsten Flanke
                        wasser_ok <= '0'; --zurücksetzen des Sensorwertes
                        
			abbruch <= '1'; --breche den Waschgang ab
			wait until pumpen = '1'; --warten auf Abpumpen
			wait for 2 ns; --etwas Zeit zum Abpumpen
			pumpen_ok <= '1'; --singalisiere, dass fertig gepumpt ist
			wait for 4 ns; --noch kurz warten, anschließend die Signale zurücksetzen
			pumpen_ok <= '0';
			abbruch <= '0';
			tuere_zu <= '0';
			wait; --beende die Stimulation
		end process stimulate;
end behave;

blatt_04/testbench.vcd
$date
	Fri Jun  9 16:58:34 2017
$end
$version
	QuestaSim Version 10.4c_5
$end
$timescale
	1ns
$end

$scope module testbench $end
$var wire 1 ! clk $end
$var wire 1 " reset $end
$var wire 1 # start $end
$var wire 1 $ abbruch $end
$var wire 1 % tuere_zu $end
$var wire 1 & wasser_ok $end
$var wire 1 ' temp_ok $end
$var wire 1 ( waschen_ok $end
$var wire 1 ) spuelen_ok $end
$var wire 1 * pumpen_taste $end
$var wire 1 + pumpen_ok $end
$var wire 1 , schleuder_taste $end
$var wire 1 - schleudern_ok $end
$var wire 1 . wasser_auf $end
$var wire 1 / heizen $end
$var wire 1 0 waschen $end
$var wire 1 1 spuelen $end
$var wire 1 2 pumpen $end
$var wire 1 3 schleudern $end
$upscope $end
$enddefinitions $end
#0
$dumpvars
0!
0"
0#
0$
0%
0&
0'
0(
0)
0*
0+
0,
0-
0.
0/
00
01
02
03
$end
#1
1!
1%
#2
0!
#3
1!
1#
#4
0!
#5
1!
1.
#6
0!
#7
1!
0#
1&
#8
0!
#9
1!
1/
0.
#10
0!
#11
1!
1'
0&
#12
0!
#13
1!
10
0/
#14
0!
#15
1!
1(
0'
#16
0!
#17
1!
11
00
#18
0!
#19
1!
1)
0(
#20
0!
#21
1!
01
#22
0!
#23
1!
0%
0)
#24
0!
#25
1!
#26
0!
#27
1!
#28
0!
#29
1!
#30
0!
#31
1!
#32
0!
#33
1!
#34
0!
#35
1!
1%
#36
0!
#37
1!
1#
#38
0!
#39
1!
1.
#40
0!
#41
1!
0#
1&
#42
0!
#43
1!
1/
0.
#44
0!
#45
1!
1"
0&
#46
0!
#47
1!
0/
#48
0!
#49
1!
#50
0!
#51
1!
0%
0"
#52
0!
#53
1!
#54
0!
#55
1!
#56
0!
#57
1!
#58
0!
#59
1!
#60
0!
#61
1!
#62
0!
#63
1!
1%
#64
0!
#65
1!
1#
#66
0!
#67
1!
1.
#68
0!
#69
1!
0#
1&
#70
0!
#71
1!
1/
0.
#72
0!
#73
1!
1$
0&
#74
0!
#75
1!
#76
0!
#77
1!
#78
0!
#79
1!
12
0/
#80
0!
#81
1!
1+
#82
0!
#83
1!
02
#84
0!
#85
1!
0%
0$
0+
#86
0!
#87
1!
12
