blatt_01/source/orgatter.vhd
LIBRARY IEEE ;
USE IEEE.std_logic_1164.all;
USE IEEE.std_logic_arith.all;
ENTITY orgatter IS
PORT ( A, B : IN BIT ;
Z : OUT BIT ) ;
END orgatter;
ARCHITECTURE behave OF orgatter IS
BEGIN
Z <= A OR B ;
END;

blatt_01/source/halfadder.vhd
LIBRARY IEEE ;
USE IEEE.std_logic_1164.all;
USE IEEE.std_logic_arith.all;
ENTITY halfadder IS
PORT ( A, B : IN BIT ;
S , C : OUT BIT ) ;
END halfadder;
ARCHITECTURE behave OF halfadder IS
BEGIN
S <= A XOR B ;
C <= A AND B ;
END;

blatt_01/source/fulladder.vhd
LIBRARY IEEE;
USE IEEE.std_logic_1164.all;
USE IEEE.std_logic_arith.all;

ENTITY fulladder IS
PORT ( A, B, C_in : IN BIT ;
S , C : OUT BIT ) ;
END fulladder;
ARCHITECTURE struct OF fulladder IS
SIGNAL i1, i2, i3 : bit;
component halfadder is
port(A,B: in bit;
S,C: out bit);
end component;
component ORGATTER
port (A, B: in bit;
Z: out bit);
end component;

BEGIN
U1:HALFADDER port map(A, B, i1, i2);
U2:HALFADDER port map(i1, C_in, S, i3);
U3:ORGATTER port map(i2, i3, C);
END;

blatt_01/simulation/vcd/fulladder_simulation.vcd
$date
	Fri May 12 15:36:37 2017
$end
$version
	QuestaSim Version 10.4c_5
$end
$timescale
	1ns
$end

$scope module fulladder $end
$var wire 1 ! A $end
$var wire 1 " B $end
$var wire 1 # C_in $end
$var wire 1 $ S $end
$var wire 1 % C $end
$var wire 1 & i1 $end
$var wire 1 ' i2 $end
$var wire 1 ( i3 $end
$upscope $end
$enddefinitions $end
#0
$dumpvars
0!
0"
0#
0$
0%
0&
0'
0(
$end
#10
1#
1$
#20
0#
1"
0$
1&
1$
#30
1#
1(
0$
1%
#40
0#
0"
1!
0(
1$
0%
#50
1#
1(
0$
1%
#60
0#
1"
0(
1$
1'
0&
0$
#70
1#
1$
#80
0!
0"
0#
0'
0$
0%
